pytest_wdl/__init__.py
pytest_wdl/core.py
pytest_wdl/fixtures.py
pytest_wdl/utils.py
pytest_wdl/data_types/__init__.py
pytest_wdl/data_types/bam.py
pytest_wdl/data_types/vcf.py
pytest_wdl/executors/__init__.py
pytest_wdl/executors/cromwell.py
tests/__init__.py
tests/test_core.py
tests/test_executors.py
tests/test_fixtures.py
tests/test_utils.py
tests/test_bam/__init__.py
tests/test_bam/test_bam.py
tests/test_vcf/__init__.py
tests/test_vcf/test_vcf.py
pytest_wdl-0.1.2.dev0.dist-info/LICENSE
pytest_wdl-0.1.2.dev0.dist-info/METADATA
pytest_wdl-0.1.2.dev0.dist-info/WHEEL
pytest_wdl-0.1.2.dev0.dist-info/entry_points.txt
pytest_wdl-0.1.2.dev0.dist-info/top_level.txt
pytest_wdl-0.1.2.dev0.dist-info/RECORD
