Metadata-Version: 2.1
Name: pytest-wdl
Version: 0.1.2.dev0
Summary: Fixtures for pytest for running WDL workflows using Cromwell.
Home-page: UNKNOWN
License: UNKNOWN
Platform: UNKNOWN
Requires-Dist: pytest
Requires-Dist: delegator.py
Provides-Extra: all
Requires-Dist: pysam ; extra == 'all'
Requires-Dist: tqdm ; extra == 'all'
Provides-Extra: bam
Requires-Dist: pysam ; extra == 'bam'
Provides-Extra: progress
Requires-Dist: tqdm ; extra == 'progress'
